hyrise/HIVDB_9.8.xml
hyrise/__init__.py
hyrise/cli.py
hyrise/hyrise.def
hyrise/commands/__init__.py
hyrise/commands/container.py
hyrise/commands/sierra.py
hyrise/core/__init__.py
hyrise/core/file_utils.py
hyrise/core/processor.py
hyrise/core/report_config.py
hyrise/core/assets/favicon.svg
hyrise/core/assets/hyrise_logo.png
hyrise/core/assets/hyrise_logo.svg
hyrise/core/assets/hyrise_logo_plain.svg
hyrise/utils/__init__.py
hyrise/utils/common_args.py
hyrise/utils/container_builder.py
hyrise/utils/container_utils.py
hyrise/utils/html_utils.py
hyrise/visualizers/__init__.py
hyrise/visualizers/hiv_visualizations.py
hyrise/visualizers/info_and_guides.py
hyrise-0.1.1.dist-info/licenses/AUTHORS.md
hyrise-0.1.1.dist-info/licenses/LICENSE
hyrise-0.1.1.dist-info/METADATA
hyrise-0.1.1.dist-info/WHEEL
hyrise-0.1.1.dist-info/entry_points.txt
hyrise-0.1.1.dist-info/top_level.txt
hyrise-0.1.1.dist-info/RECORD
