Metadata-Version: 2.4
Name: hyrise
Version: 0.1.1
Summary: HIV Resistance Interpretation and Visualization System - A comprehensive tool for HIV drug resistance analysis and visualization
Home-page: https://github.com/phac-nml/HyRISE
Author: Gurasis Osahan
Author-email: gurasis.osahan@phac-aspc.gc.ca
License: GPL-3.0-or-later
Project-URL: Source, https://github.com/phac-nml/HyRISE
Project-URL: Tracker, https://github.com/phac-nml/HyRISE/-/issues
Project-URL: Documentation, https://github.com/phac-nml/HyRISE/wiki
Project-URL: Publication, https://github.com/phac-nml/HyRISE#citation
Project-URL: Contact, https://github.com/phac-nml/HyRISE#contact
Keywords: hiv drug-resistance genomics bioinformatics visualization multiqc sierra hiv-sequence analysis mutation
Classifier: Development Status :: 4 - Beta
Classifier: Intended Audience :: Developers
Classifier: Intended Audience :: Science/Research
Classifier: Intended Audience :: Healthcare Industry
Classifier: Topic :: Scientific/Engineering :: Bio-Informatics
Classifier: Topic :: Scientific/Engineering :: Medical Science Apps.
Classifier: Topic :: Scientific/Engineering :: Information Analysis
Classifier: Topic :: Software Development :: Libraries :: Python Modules
Classifier: Topic :: System :: Distributed Computing
Classifier: Operating System :: OS Independent
Classifier: Operating System :: POSIX :: Linux
Classifier: Natural Language :: English
Classifier: Environment :: Console
Classifier: Framework :: Pytest
Classifier: License :: OSI Approved :: GNU General Public License v3 or later (GPLv3+)
Classifier: Programming Language :: Python :: 3
Classifier: Programming Language :: Python :: 3.8
Classifier: Programming Language :: Python :: 3.9
Classifier: Programming Language :: Python :: 3.10
Classifier: Programming Language :: Python :: 3.11
Requires-Python: <=3.11
License-File: LICENSE
License-File: AUTHORS.md
Requires-Dist: annotated-types>=0.7.0
Requires-Dist: anyio>=4.9.0
Requires-Dist: attrs>=25.3.0
Requires-Dist: beautifulsoup4>=4.13.4
Requires-Dist: bio>=1.7.1
Requires-Dist: biopython>=1.85
Requires-Dist: biothings-client>=0.4.1
Requires-Dist: build>=1.2.2.post1
Requires-Dist: certifi>=2025.1.31
Requires-Dist: charset-normalizer>=3.4.1
Requires-Dist: click>=8.1.8
Requires-Dist: coloredlogs>=15.0.1
Requires-Dist: colormath2>=3.0.3
Requires-Dist: contourpy>=1.3.2
Requires-Dist: coverage[toml]>=7.8.0
Requires-Dist: cycler>=0.12.1
Requires-Dist: exceptiongroup>=1.2.2
Requires-Dist: fonttools>=4.57.0
Requires-Dist: gprofiler-official>=1.0.0
Requires-Dist: h11>=0.14.0
Requires-Dist: httpcore>=1.0.8
Requires-Dist: httpx>=0.28.1
Requires-Dist: humanfriendly>=10.0
Requires-Dist: humanize>=4.12.2
Requires-Dist: idna>=3.10
Requires-Dist: importlib-metadata>=8.6.1
Requires-Dist: iniconfig>=2.1.0
Requires-Dist: jinja2>=3.1.6
Requires-Dist: jsonschema>=4.23.0
Requires-Dist: jsonschema-specifications>=2024.10.1
Requires-Dist: kaleido>=0.2.1
Requires-Dist: kiwisolver>=1.4.8
Requires-Dist: markdown>=3.8
Requires-Dist: markdown-it-py>=3.0.0
Requires-Dist: markupsafe>=3.0.2
Requires-Dist: matplotlib>=3.10.1
Requires-Dist: mdurl>=0.1.2
Requires-Dist: multiqc>=1.28
Requires-Dist: mygene>=3.2.2
Requires-Dist: narwhals>=1.35.0
Requires-Dist: natsort>=8.4.0
Requires-Dist: networkx>=3.4.2
Requires-Dist: numpy<2.0.0,>=1.24.3
Requires-Dist: packaging>=25.0
Requires-Dist: pandas>=2.2.3
Requires-Dist: pillow>=11.2.1
Requires-Dist: pip-tools>=7.4.1
Requires-Dist: platformdirs>=4.3.7
Requires-Dist: plotly>=6.0.1
Requires-Dist: pluggy>=1.5.0
Requires-Dist: poetry-core>=2.1.2
Requires-Dist: pooch>=1.8.2
Requires-Dist: pydantic>=2.11.3
Requires-Dist: pydantic-core>=2.33.1
Requires-Dist: pygments>=2.19.1
Requires-Dist: pyparsing>=3.2.3
Requires-Dist: pyproject-hooks>=1.2.0
Requires-Dist: pytest>=8.3.5
Requires-Dist: pytest-cov>=6.1.1
Requires-Dist: python-dateutil>=2.9.0.post0
Requires-Dist: python-dotenv>=1.1.0
Requires-Dist: pytz>=2025.2
Requires-Dist: pyyaml>=6.0.2
Requires-Dist: referencing>=0.36.2
Requires-Dist: regex>=2024.11.6
Requires-Dist: requests>=2.32.3
Requires-Dist: rich>=14.0.0
Requires-Dist: rich-click>=1.8.8
Requires-Dist: rpds-py>=0.24.0
Requires-Dist: seaborn>=0.13.2
Requires-Dist: six>=1.17.0
Requires-Dist: sniffio>=1.3.1
Requires-Dist: soupsieve>=2.7
Requires-Dist: spectra>=0.1.0
Requires-Dist: tabulate>=0.9.0
Requires-Dist: tiktoken>=0.9.0
Requires-Dist: tomli>=2.2.1
Requires-Dist: tqdm>=4.67.1
Requires-Dist: typeguard>=4.4.2
Requires-Dist: typing-extensions>=4.13.2
Requires-Dist: typing-inspection>=0.4.0
Requires-Dist: tzdata>=2025.2
Requires-Dist: urllib3>=2.4.0
Requires-Dist: wheel>=0.45.1
Requires-Dist: zipp>=3.21.0
Dynamic: author
Dynamic: author-email
Dynamic: classifier
Dynamic: description
Dynamic: description-content-type
Dynamic: home-page
Dynamic: keywords
Dynamic: license
Dynamic: license-file
Dynamic: project-url
Dynamic: requires-dist
Dynamic: requires-python
Dynamic: summary
